flask_sqlalchemy_session/__init__.py
Flask_SQLAlchemy_Session2024-3.0.0.dist-info/AUTHORS
Flask_SQLAlchemy_Session2024-3.0.0.dist-info/LICENSE
Flask_SQLAlchemy_Session2024-3.0.0.dist-info/METADATA
Flask_SQLAlchemy_Session2024-3.0.0.dist-info/WHEEL
Flask_SQLAlchemy_Session2024-3.0.0.dist-info/top_level.txt
Flask_SQLAlchemy_Session2024-3.0.0.dist-info/RECORD
