Metadata-Version: 2.1
Name: Flask-SQLAlchemy-Session2024
Version: 3.0.0
Summary: SQL Alchemy session scoped on Flask requests.
Home-page: https://github.com/e-c-d/flask-sqlalchemy-session2024
Author: Eduard Christian Dumitrescu
Author-email: eduard.c.dumitrescu@gmail.com
License: MIT
Classifier: Development Status :: 5 - Production/Stable
Classifier: Intended Audience :: Developers
Classifier: Environment :: Web Environment
Classifier: License :: OSI Approved :: MIT License
Classifier: Programming Language :: Python :: 2
Classifier: Programming Language :: Python :: 3
Classifier: Topic :: Internet :: WWW/HTTP :: Dynamic Content
Classifier: Topic :: Software Development :: Libraries :: Python Modules
License-File: LICENSE
License-File: AUTHORS
Requires-Dist: Flask
Requires-Dist: Werkzeug
Requires-Dist: sqlalchemy
Provides-Extra: docs
Requires-Dist: Sphinx ; extra == 'docs'
Requires-Dist: alabaster ; extra == 'docs'
